cr39py/__init__.py
cr39py/core/__init__.py
cr39py/core/ci.py
cr39py/core/data.py
cr39py/core/exportable_class.py
cr39py/core/types.py
cr39py/core/units.py
cr39py/core/data/calibration/wrf_calibrations.yml
"cr39py/core/data/nuclear/D(D,n)He-3.h5"
"cr39py/core/data/nuclear/D(D,p)T.h5"
"cr39py/core/data/nuclear/He-3(D,p)A.h5"
cr39py/core/data/srim/Deuteron in Al.txt
cr39py/core/data/srim/Deuteron in Borosilicate.txt
cr39py/core/data/srim/Deuteron in CR-39.txt
cr39py/core/data/srim/Deuteron in Mylar.txt
cr39py/core/data/srim/Deuteron in Polycarbonate.txt
cr39py/core/data/srim/Deuteron in Ta.txt
cr39py/core/data/srim/Deuteron in W.txt
cr39py/core/data/srim/Proton in Al.txt
cr39py/core/data/srim/Proton in Borosilicate.txt
cr39py/core/data/srim/Proton in CR-39.txt
cr39py/core/data/srim/Proton in Mylar.txt
cr39py/core/data/srim/Proton in Polycarbonate.txt
cr39py/core/data/srim/Proton in Ta.txt
cr39py/core/data/srim/Proton in W.txt
cr39py/core/data/srim/Triton in Al.txt
cr39py/core/data/srim/Triton in Borosilicate.txt
cr39py/core/data/srim/Triton in CR-39.txt
cr39py/core/data/srim/Triton in Mylar.txt
cr39py/core/data/srim/Triton in Polycarbonate.txt
cr39py/core/data/srim/Triton in Ta.txt
cr39py/core/data/srim/Triton in W.txt
cr39py/core/data/srim/proton_Al_remove_ranging.h5
cr39py/core/data/test/test_alphas.cpsa
cr39py/core/data/test/test_wrf_G093_6hr.cpsa
cr39py/etch/__init__.py
cr39py/etch/tools.py
cr39py/filtration/__init__.py
cr39py/filtration/layer.py
cr39py/filtration/srim.py
cr39py/filtration/stack.py
cr39py/models/__init__.py
cr39py/models/fusion.py
cr39py/models/response.py
cr39py/scan/__init__.py
cr39py/scan/_cli.py
cr39py/scan/base_scan.py
cr39py/scan/cpsa.py
cr39py/scan/cut.py
cr39py/scan/subset.py
cr39py/scan/wrf.py
cr39py-0.0.2.dist-info/LICENSE
cr39py-0.0.2.dist-info/METADATA
cr39py-0.0.2.dist-info/WHEEL
cr39py-0.0.2.dist-info/top_level.txt
cr39py-0.0.2.dist-info/RECORD
